jrnl_search/__init__.py
jrnl_search/__main__.py
jrnl_search/config.py
jrnl_search/display.py
jrnl_search/main.py
jrnl_search/parse_args.py
jrnl_search/search.py
jrnl_search-0.1.1.dist-info/LICENSE.md
jrnl_search-0.1.1.dist-info/METADATA
jrnl_search-0.1.1.dist-info/WHEEL
jrnl_search-0.1.1.dist-info/entry_points.txt
jrnl_search-0.1.1.dist-info/RECORD
