Metadata-Version: 2.1
Name: jrnl-search
Version: 0.1.1
Summary: 
Author: Carl Kolon
Author-email: carl@kolon.org
Requires-Python: >=3.10.0,<3.13
Classifier: Environment :: Console
Classifier: License :: OSI Approved :: GNU General Public License v3 (GPLv3)
Classifier: Operating System :: OS Independent
Classifier: Programming Language :: Python :: 3
Classifier: Programming Language :: Python :: 3.10
Classifier: Programming Language :: Python :: 3.11
Classifier: Programming Language :: Python :: 3.12
Classifier: Topic :: Office/Business :: News/Diary
Requires-Dist: jrnl (>=4.0,<5.0)
Requires-Dist: numpy (>=1.21.2,<2.0.0)
Requires-Dist: rich (>=13.7.0,<14.0.0)
Requires-Dist: sentence-transformers (>=2.1.0,<3.0.0)
